odoo/addons/budget_plan_detail_purchase_requisition/README.rst
odoo/addons/budget_plan_detail_purchase_requisition/__init__.py
odoo/addons/budget_plan_detail_purchase_requisition/__manifest__.py
odoo/addons/budget_plan_detail_purchase_requisition/hooks.py
odoo/addons/budget_plan_detail_purchase_requisition/models/__init__.py
odoo/addons/budget_plan_detail_purchase_requisition/models/account_analytic_dimension.py
odoo/addons/budget_plan_detail_purchase_requisition/models/purchase_requisition.py
odoo/addons/budget_plan_detail_purchase_requisition/readme/CONTRIBUTORS.md
odoo/addons/budget_plan_detail_purchase_requisition/readme/DESCRIPTION.md
odoo/addons/budget_plan_detail_purchase_requisition/static/description/icon.png
odoo/addons/budget_plan_detail_purchase_requisition/static/description/index.html
odoo/addons/budget_plan_detail_purchase_requisition/tests/__init__.py
odoo/addons/budget_plan_detail_purchase_requisition/tests/test_budget_plan_detail_purchase_requisition.py
odoo/addons/budget_plan_detail_purchase_requisition/views/purchase_requisition_view.xml
odoo/addons/budget_plan_detail_purchase_requisition/wizard/__init__.py
odoo/addons/budget_plan_detail_purchase_requisition/wizard/purchase_request_line_make_purchase_requisition.py
odoo_addon_budget_plan_detail_purchase_requisition-18.0.1.0.2.dist-info/METADATA
odoo_addon_budget_plan_detail_purchase_requisition-18.0.1.0.2.dist-info/WHEEL
odoo_addon_budget_plan_detail_purchase_requisition-18.0.1.0.2.dist-info/top_level.txt
odoo_addon_budget_plan_detail_purchase_requisition-18.0.1.0.2.dist-info/RECORD
