Metadata-Version: 2.1
Name: odoo-addon-budget_plan_detail_purchase_requisition
Version: 18.0.1.0.2
Requires-Python: >=3.10
Requires-Dist: odoo-addon-budget_plan_detail_purchase_request==18.0.*
Requires-Dist: odoo-addon-purchase_request_to_requisition==18.0.*
Requires-Dist: odoo==18.0.*
Summary: Budget Plan Detail - Purchase Requisition
Home-page: https://github.com/ecosoft-odoo/budgeting
License: AGPL-3
Author: Ecosoft, Odoo Community Association (OCA)
Author-email: support@odoo-community.org
Classifier: Programming Language :: Python
Classifier: Framework :: Odoo
Classifier: Framework :: Odoo :: 18.0
Classifier: License :: OSI Approved :: GNU Affero General Public License v3
Classifier: Development Status :: 3 - Alpha
